<?xml version="1.0" encoding="utf-8"?>
<openerp>
<data>
	<record id="view_res_partner_invoice_line_button_form" model="ir.ui.view">
		<field name="name">res.partner.invoice.line.button.form</field>
		<field name="model">res.partner</field>
		<field name="inherit_id" ref="base.view_partner_form"/>
		<field eval="18" name="priority"/>
		<field name="arch" type="xml">
            <xpath expr="//div[@name='buttons']" position="inside">
				<button name="show_lines" string="Show invoice lines" type="object" groups="account.group_account_invoice"/>
			</xpath>
            
            <!-- Redefine how contracts are shown. -->
            <xpath expr="//page[@string='Contracts']" position="replace"/>
            <xpath expr="//page[@string='Correspondance']" position="before">
                <page string="Sponsorships" groups="child_compassion.group_sponsorship">
                    <button name="create_contract" string="Add" type="object"/>
                    <field name="contracts_fully_managed" invisible="True" />
                    <field name="contracts_paid" invisible="True" />
                    <field name="contracts_correspondant" invisible="True" />
                    <div attrs="{'invisible' : [('contracts_paid','=', [])]}">
                        <h3>Sponsorships as payer only</h3>
                        <field name="contracts_paid" context="{'partner_contracts_view': True, 'default_type': 'S'}" />
                    </div>
                    <div attrs="{'invisible' : [('contracts_correspondant','=', [])]}">
                        <h3>Sponsorships as correspondent only</h3>
                        <field name="contracts_correspondant" context="{'partner_contracts_view': True, 'default_type': 'S'}" />
                    </div>
                    <div attrs="{'invisible' : [('contracts_fully_managed','=', [])]}">
                        <h3>Sponsorships fully managed</h3>
                        <field name="contracts_fully_managed" context="{'partner_contracts_view': True, 'default_type': 'S'}" />
                    </div>
                    <div attrs="{'invisible' : [('other_contract_ids','=', [])]}">
                        <h3>Other contracts</h3>
                        <field name="other_contract_ids" context="{'partner_contracts_view': True, 'default_type': 'O'}" />
                    </div>
                </page>
            </xpath>
            
		</field>
	</record>
     <record id="compassion_partner_view_buttons" model="ir.ui.view">
            <field name="name">compassion.partner.view.buttons</field>
            <field name="model">res.partner</field>
            <field name="inherit_id" ref="sale.res_partner_view_buttons" />
            <field name="arch" type="xml">
                <xpath expr="//button[@name='%(sale.act_res_partner_2_sale_order)d']" position="replace">
                    <button name="unreconciled_transaction_items" string='Unreconciled Transaction Items' type='object' groups="account.group_account_user"/>
                    <button name="receivable_transaction_items" string='1050 Transaction Items' type='object' groups="account.group_account_user"/>
                </xpath>
            </field>
    </record>
</data>
</openerp>
