<odoo>
  <record id="view_correspondence_crosscheck" model="ir.ui.view">
    <field name="name">correspondence.template.crosscheck.form</field>
    <field name="model">correspondence.template.crosscheck</field>
    <field name="arch" type="xml">
      <form string="Correspondence Crosscheck">
        <field name="file_"/>
      </form>
    </field>
  </record>

<!--  <record id="view_crosscheck_image_tree" model="ir.ui.view">-->
<!--    <field name="name">crosscheck.image.tree</field>-->
<!--    <field name="model">crosscheck.image</field>-->
<!--    <field name="arch" type="xml">-->
<!--      <tree string="Image crosschecked" edit="false" create="false">-->
<!--        <field name="name"/>-->
<!--        <field name="image" widget="image" display="icon"/>-->
<!--      </tree>-->
<!--    </field>-->
<!--  </record>-->
</odoo>
